cirq_google/__init__.py
cirq_google/_version.py
cirq_google/_version_test.py
cirq_google/conftest.py
cirq_google/json_resolver_cache.py
cirq_google/py.typed
cirq_google/api/__init__.py
cirq_google/api/v1/__init__.py
cirq_google/api/v1/operations.proto
cirq_google/api/v1/operations_pb2.py
cirq_google/api/v1/operations_pb2.pyi
cirq_google/api/v1/params.proto
cirq_google/api/v1/params.py
cirq_google/api/v1/params_pb2.py
cirq_google/api/v1/params_pb2.pyi
cirq_google/api/v1/params_test.py
cirq_google/api/v1/program.proto
cirq_google/api/v1/program_pb2.py
cirq_google/api/v1/program_pb2.pyi
cirq_google/api/v1/programs.py
cirq_google/api/v1/programs_test.py
cirq_google/api/v1/proto_test.py
cirq_google/api/v2/__init__.py
cirq_google/api/v2/batch.proto
cirq_google/api/v2/batch_pb2.py
cirq_google/api/v2/batch_pb2.pyi
cirq_google/api/v2/calibration.proto
cirq_google/api/v2/calibration_pb2.py
cirq_google/api/v2/calibration_pb2.pyi
cirq_google/api/v2/device.proto
cirq_google/api/v2/device_pb2.py
cirq_google/api/v2/device_pb2.pyi
cirq_google/api/v2/metrics.proto
cirq_google/api/v2/metrics_pb2.py
cirq_google/api/v2/metrics_pb2.pyi
cirq_google/api/v2/ndarrays.proto
cirq_google/api/v2/ndarrays.py
cirq_google/api/v2/ndarrays_pb2.py
cirq_google/api/v2/ndarrays_pb2.pyi
cirq_google/api/v2/ndarrays_test.py
cirq_google/api/v2/program.proto
cirq_google/api/v2/program.py
cirq_google/api/v2/program_pb2.py
cirq_google/api/v2/program_pb2.pyi
cirq_google/api/v2/program_test.py
cirq_google/api/v2/proto_test.py
cirq_google/api/v2/result.proto
cirq_google/api/v2/result_pb2.py
cirq_google/api/v2/result_pb2.pyi
cirq_google/api/v2/results.py
cirq_google/api/v2/results_test.py
cirq_google/api/v2/run_context.proto
cirq_google/api/v2/run_context.py
cirq_google/api/v2/run_context_pb2.py
cirq_google/api/v2/run_context_pb2.pyi
cirq_google/api/v2/run_context_test.py
cirq_google/api/v2/sweeps.py
cirq_google/api/v2/sweeps_test.py
cirq_google/cloud/__init__.py
cirq_google/cloud/quantum/__init__.py
cirq_google-1.6.0.dist-info/licenses/LICENSE
cirq_google-1.6.0.dist-info/METADATA
cirq_google-1.6.0.dist-info/WHEEL
cirq_google-1.6.0.dist-info/top_level.txt
cirq_google-1.6.0.dist-info/RECORD
